{
  "type": "FeatureCollection",
  "name": "elevation_points",
  "_source": "Sample DEM samples approximating SRTM (metres above sea level). Illustrative only.",
  "crs": { "type": "name", "properties": { "name": "urn:ogc:def:crs:OGC:1.3:CRS84" } },
  "features": [
    { "type": "Feature", "properties": { "elevation_m": 1680 }, "geometry": { "type": "Point", "coordinates": [36.78, -1.33] } },
    { "type": "Feature", "properties": { "elevation_m": 1660 }, "geometry": { "type": "Point", "coordinates": [36.82, -1.35] } },
    { "type": "Feature", "properties": { "elevation_m": 1640 }, "geometry": { "type": "Point", "coordinates": [36.85, -1.37] } },
    { "type": "Feature", "properties": { "elevation_m": 1620 }, "geometry": { "type": "Point", "coordinates": [36.88, -1.39] } },
    { "type": "Feature", "properties": { "elevation_m": 1600 }, "geometry": { "type": "Point", "coordinates": [36.92, -1.40] } },
    { "type": "Feature", "properties": { "elevation_m": 1700 }, "geometry": { "type": "Point", "coordinates": [36.80, -1.30] } },
    { "type": "Feature", "properties": { "elevation_m": 1580 }, "geometry": { "type": "Point", "coordinates": [36.90, -1.45] } },
    { "type": "Feature", "properties": { "elevation_m": 2100 }, "geometry": { "type": "Point", "coordinates": [36.65, -1.38] } },
    { "type": "Feature", "properties": { "elevation_m": 1550 }, "geometry": { "type": "Point", "coordinates": [36.95, -1.47] } },
    { "type": "Feature", "properties": { "elevation_m": 1610 }, "geometry": { "type": "Point", "coordinates": [36.86, -1.43] } }
  ]
}
